django_simple_auth-0.2.1.dist-info/DESCRIPTION.rst
django_simple_auth-0.2.1.dist-info/METADATA
django_simple_auth-0.2.1.dist-info/RECORD
django_simple_auth-0.2.1.dist-info/WHEEL
django_simple_auth-0.2.1.dist-info/metadata.json
django_simple_auth-0.2.1.dist-info/top_level.txt
simple_auth/__init__.py
simple_auth/admin.py
simple_auth/apps.py
simple_auth/forms.py
simple_auth/middleware.py
simple_auth/models.py
simple_auth/urls.py
simple_auth/views.py
simple_auth/migrations/0001_initial.py
simple_auth/migrations/__init__.py
simple_auth/templates/simple_auth/password_form.html
