Metadata-Version: 2.0
Name: django-simple-auth
Version: 0.2.1
Summary: Simple password-only protection
Home-page: https://github.com/bennylope/django-simple-auth
Author: Ben Lopatin
Author-email: ben@benlopatin.com
License: BSD License
Platform: OS Independent
Classifier: Development Status :: 4 - Beta
Classifier: Environment :: Web Environment
Classifier: Intended Audience :: Developers
Classifier: License :: OSI Approved :: BSD License
Classifier: Operating System :: OS Independent
Classifier: Programming Language :: Python
Classifier: Programming Language :: Python :: 2.7
Classifier: Programming Language :: Python :: 3.4
Classifier: Programming Language :: Python :: 3.5
Classifier: Framework :: Django
